arretify/__init__.py
arretify/errors.py
arretify/main.py
arretify/main_test.py
arretify/pipeline.py
arretify/pipeline_test.py
arretify/semantic_tag_specs.py
arretify/semantic_tag_specs_test.py
arretify/settings.py
arretify/types.py
arretify/types_test.py
arretify/_vendor/README.md
arretify/_vendor/mistralai.py
arretify/_vendor/clients_api_droit/.git
arretify/_vendor/clients_api_droit/.gitignore
arretify/_vendor/clients_api_droit/README.md
arretify/_vendor/clients_api_droit/pyproject.toml
arretify/_vendor/clients_api_droit/clients_api_droit/__init__.py
arretify/_vendor/clients_api_droit/clients_api_droit/common.py
arretify/_vendor/clients_api_droit/clients_api_droit/eurlex-ws.xml
arretify/_vendor/clients_api_droit/clients_api_droit/eurlex.py
arretify/_vendor/clients_api_droit/clients_api_droit/legifrance.py
arretify/law_data/__init__.py
arretify/law_data/eurlex_constants.py
arretify/law_data/french_addresses.py
arretify/law_data/legifrance_constants.py
arretify/law_data/apis/__init__.py
arretify/law_data/apis/eurlex.py
arretify/law_data/apis/legifrance.py
arretify/law_data/apis/mistral.py
arretify/law_data/french_addresses/street_names.json
arretify/law_data/legifrance/code_index_LEGITEXT000006072050.json
arretify/law_data/legifrance/code_index_LEGITEXT000006074220.json
arretify/law_data/legifrance/codes.json
arretify/parsing_utils/__init__.py
arretify/parsing_utils/dates.py
arretify/parsing_utils/dates_test.py
arretify/parsing_utils/numbering.py
arretify/parsing_utils/numbering_test.py
arretify/parsing_utils/patterns.py
arretify/parsing_utils/patterns_test.py
arretify/regex_utils/__init__.py
arretify/regex_utils/core.py
arretify/regex_utils/core_test.py
arretify/regex_utils/functional.py
arretify/regex_utils/functional_test.py
arretify/regex_utils/helpers.py
arretify/regex_utils/helpers_test.py
arretify/regex_utils/merge.py
arretify/regex_utils/merge_test.py
arretify/regex_utils/split.py
arretify/regex_utils/split_test.py
arretify/regex_utils/types.py
arretify-0.1.0.dist-info/METADATA
arretify-0.1.0.dist-info/WHEEL
arretify-0.1.0.dist-info/entry_points.txt
arretify-0.1.0.dist-info/licenses/LICENSE
arretify-0.1.0.dist-info/RECORD
