Metadata-Version: 2.4
Name: arretify
Version: 0.1.0
Summary: Arrêtify est une librairie Python permettant la conversion d'arrêtés préfectoraux français en HTML sémantique.
Project-URL: Homepage, https://github.com/mte-dgpr/arretify
Project-URL: Issues, https://github.com/mte-dgpr/arretify/issues
Author-email: Sébastien Piquemal <sebastien.piquemal@developpement-durable.gouv.fr>, Sébastien Meyer <sebastien.meyer@developpement-durable.gouv.fr>
License-Expression: Apache-2.0
License-File: LICENSE
Requires-Python: ~=3.12
Requires-Dist: beautifulsoup4~=4.13
Requires-Dist: lxml~=5.3
Requires-Dist: markdown~=3.7
Requires-Dist: mistralai~=1.8
Requires-Dist: pydantic~=2.11
Requires-Dist: pylatexenc~=2.10
Requires-Dist: python-dotenv~=1.0
Requires-Dist: requests-cache~=1.2
Requires-Dist: requests~=2.32
Requires-Dist: roman~=5.0
Requires-Dist: spacy~=3.8.7
Requires-Dist: zeep~=4.3
Provides-Extra: dev
Requires-Dist: autoflake~=2.3; extra == 'dev'
Requires-Dist: black~=25.1; extra == 'dev'
Requires-Dist: flake8-bugbear~=24.12; extra == 'dev'
Requires-Dist: flake8-isort~=7.0; extra == 'dev'
Requires-Dist: flake8~=7.2; extra == 'dev'
Requires-Dist: isort~=7.0; extra == 'dev'
Requires-Dist: licenseheaders~=0.8.8; extra == 'dev'
Requires-Dist: mypy~=1.15; extra == 'dev'
Requires-Dist: pre-commit~=4.2; extra == 'dev'
Requires-Dist: pytest~=8.3; extra == 'dev'
Requires-Dist: types-beautifulsoup4~=4.12; extra == 'dev'
Requires-Dist: types-markdown~=3.7; extra == 'dev'
Requires-Dist: types-requests~=2.32; extra == 'dev'
